{"wKwuXlc0MokPtgvitG1veQ==":"accounting-aerial-application-bankbook-business-cc0-1452879-pxhere.com-2000x1219.jpg","2n99wMtwPWp9qVprHs8fAg==":"restu-mobile-large-960x560.jpg","+FCp4/kJyYm2oXTLB228Kg==":"cutie-jewellery-large-960x560.jpg","og1XrXnics+6EJDk3aw7NA==":"ctauthorcup-large-960x560.jpg","GeYRW5QK+yTLTZH49wHqGQ==":"mujjo-large-960x560.jpg","aFLCji/i1SguMsEHsDvnyg==":"heureka-mobile-large-960x560.jpg","nsjcvMn4ksHSmiTogx2BnA==":"computer-work-hand-man-person-people-625568-pxhere.com-2000x1331.jpg","6sSyF4kBVMOp3vVR5Yh5GA==":"about-1347x519.jpg","Ib7MsdNbulGaSTUBIcb45A==":"about-1-1347x519.jpg","OvJO7vRsU1Q6kwA5Y1kTSw==":"logo-122x122.jpg","Jiy0YG9+iVjvB1iSg0dQGw==":"logo-1-122x122.jpg"}